{
  "fan_max_speed": [
    "100"
  ],
  "fan_min_speed": [
    "20"
  ],
  "filament_max_volumetric_speed": [
    "16"
  ],
  "filament_retraction_length": [
    "0.8"
  ],
  "filament_settings_id": [
    "Fill-3D PLA Basic"
  ],
  "from": "User",
  "hot_plate_temp": [
    "55"
  ],
  "hot_plate_temp_initial_layer": [
    "55"
  ],
  "inherits": "Creality Generic PLA",
  "is_custom_defined": "0",
  "name": "Fill-3D PLA Basic",
  "nozzle_temperature": [
    "220"
  ],
  "nozzle_temperature_initial_layer": [
    "220"
  ],
  "nozzle_temperature_range_low": [
    "210"
  ],
  "slow_down_layer_time": [
    "5"
  ],
  "version": "2.2.0.4"
}